{
    "name": "AlarmInfo",
    "fields": [
        {
            "fieldName": "time",
            "fieldType": "Instant",
            "fieldValidateRules": [
                "required"
            ]
        },
        {
            "fieldName": "priority",
            "fieldType": "Integer",
            "fieldValidateRules": [
                "required"
            ]
        },
        {
            "fieldName": "comment",
            "fieldType": "String"
        }
    ],
    "relationships": [
        {
            "relationshipType": "one-to-one",
            "relationshipName": "placeOfAction",
            "otherEntityName": "placeOfAction",
            "otherEntityField": "id",
            "ownerSide": true,
            "otherEntityRelationshipName": "alarmInfo"
        },
        {
            "relationshipType": "one-to-one",
            "relationshipName": "keywords",
            "otherEntityName": "keywords",
            "otherEntityField": "id",
            "ownerSide": true,
            "otherEntityRelationshipName": "alarmInfo"
        },
        {
            "relationshipType": "one-to-many",
            "relationshipName": "resources",
            "otherEntityName": "resource",
            "otherEntityRelationshipName": "alarmInfo"
        }
    ],
    "changelogDate": "20180922223601",
    "entityTableName": "alarm_info",
    "dto": "no",
    "pagination": "no",
    "service": "no",
    "jpaMetamodelFiltering": false,
    "fluentMethods": true,
    "clientRootFolder": "",
    "applications": "*"
}